Exercise1/Moore/pump_ctrl.v
module pump_ctrl (
    B1,      //Last Activated Pump was B1
    B2,      //Last Activated Pump was B2
    use_pump,   //Armed Pump
    clk,        //Clock
    reset       //Reset
);

//Definición I/O
input B1, B2, clk, reset;
output use_pump;

//Definición de Datos
    //Input Data Type
wire B1, B2, clk, reset;
    //Output Data Type
reg use_pump;

//Internal Constants
parameter s_LP1 = 1'b0;
parameter s_LP2 = 1'b1;

//Internal Variables
reg curr_state;
wire next_state;

//Code
assign next_state = fsm_function(curr_state,B1,B2);

//Function Code
function fsm_function;
    input curr_state;
    input B1;
    input B2;
    case (curr_state)
        s_LP1: if(B1 == 1'b0 && B2 == 1'b1) begin
                fsm_function = s_LP2;
                end
                else begin
                fsm_function = s_LP1;
                end
        s_LP2: if(B1 == 1'b1 && B2 == 1'b0) begin
                fsm_function = s_LP1;
                end
                else begin
                fsm_function = s_LP2;
                end
      default: fsm_function = s_LP1;
    endcase
endfunction

//Sequential Logic (synchronous to clock)
always @(posedge clk or reset)
begin: FSM_SEQ
    if(reset == 1'b1) begin
        curr_state <= #1 s_LP1;
    end else begin
        curr_state <= #1 next_state;
    end
end

//Output Logic (not synchronous to clock)
always @(*)
begin: OUTPUT_LOGIC
    if (reset == 1'b1) begin
        use_pump <= #1 1'b0;
    end else begin
        case (curr_state)
            s_LP1: use_pump <= #1 1'b1;
            s_LP2: use_pump <= #1 1'b0;
            default: use_pump <= #1 1'b0;
        endcase
    end
end

//Module End
endmodule

Exercise1/Moore/pump_ctrl_tb.v
`include "./pump_ctrl.v"

module pump_ctrl_tb ();
reg B1, B2, clk, reset;
wire P;

pump_ctrl test_module (
    .B1(B1),
    .B2(B2),
    .use_pump(P),
    .clk(clk),
    .reset(reset)
);

initial begin
    clk = 0;
    B1 = 0;
    B2 = 0;
    reset = 1;
    #6 reset = 0;
    #41 reset = 1;
    #10 reset = 0;
end

always begin
    #5 clk = !clk;
end

initial begin
  $dumpfile("pump.vcd");
  $dumpvars;
end

initial begin
  $display("Clk \tB1 \tB2 \tP");
  $monitor("%b\t%b\t%b\t%b",clk,B1,B2,P);
end

initial begin
  #4 B1 = 1; B2 = 0;
  #10 B1 = 0; B2 = 1;
  #2 B1 = 1; B2 = 0;
  #8 B1 = 0; B2 = 1;
  #20 B1 = 1; B2 = 1;
  #20 B1 = 1; B2 = 0;
  #20 B1 = 0; B2 = 0;
  #10 B1 = 1; B2 = 1;
  #10 B1 = 1; B2 = 0;
  #10 B1 = 0; B2 = 1;
end

initial begin
  #200 $finish;
end

endmodule

Exercise1/Moore/pump.vcd
$date
	Mon Nov  5 17:48:17 2018
$end
$version
	Icarus Verilog
$end
$timescale
	1s
$end
$scope module pump_ctrl_tb $end
$var wire 1 ! P $end
$var reg 1 " B1 $end
$var reg 1 # B2 $end
$var reg 1 $ clk $end
$var reg 1 % reset $end
$scope module test_module $end
$var wire 1 " B1 $end
$var wire 1 # B2 $end
$var wire 1 $ clk $end
$var wire 1 % reset $end
$var wire 1 & next_state $end
$var reg 1 ' curr_state $end
$var reg 1 ! use_pump $end
$scope function fsm_function $end
$var reg 1 ( B1 $end
$var reg 1 ) B2 $end
$var reg 1 * curr_state $end
$var reg 1 + fsm_function $end
$upscope $end
$scope begin FSM_SEQ $end
$upscope $end
$scope begin OUTPUT_LOGIC $end
$upscope $end
$upscope $end
$upscope $end
$enddefinitions $end
#0
$dumpvars
0+
x*
0)
0(
x'
0&
1%
0$
0#
0"
x!
$end
#1
0*
0!
0'
#4
1(
1"
#5
1$
#6
0%
#7
1!
#10
0$
#14
1&
1+
1)
0(
1#
0"
#15
1$
#16
1*
1'
0&
0+
0)
1(
0#
1"
#17
0!
#20
0$
#24
1&
1+
1)
0(
1#
0"
#25
1$
#30
0$
#35
1$
#40
0$
#44
1(
1"
#45
1$
#47
1%
#48
0&
0+
0*
0'
#50
0$
#55
1$
#57
0%
#58
1!
#60
0$
#64
0)
0#
#65
1$
#70
0$
#75
1$
#80
0$
#84
0(
0"
#85
1$
#90
0$
#94
1)
1(
1#
1"
#95
1$
#100
0$
#104
0)
0#
#105
1$
#110
0$
#114
1&
1+
1)
0(
1#
0"
#115
1$
#116
1*
1'
#117
0!
