Exercise2/Mealy/Mealy00.v
module Mealy00  (Clock, Resetn, w, z);

    input Clock, Resetn, w;
    output reg z;
    reg [3:1] y, Y;                    //y: Present State. Y: Next State.
    parameter [3:1] A=3'b000,B=3'b001,C=3'b010,D=3'b011,E=3'b100;
    initial y=3'b000;
    initial Y=3'b000;

    //Defines the next state combinational circuit
    always @(w,y)
        case(y)
            A: if(w) begin
                z=0;
                Y=B;
            end
            else begin
                z=0;
                Y=A;
            end
            B: if(w) begin
                z=0;
                Y=C;
            end
            else begin
                z=0;
                Y=A;
            end
            C: if(w) begin
                z=0;
                Y=C;
            end
            else begin
                z=0;
                Y=D;
            end
            D: if(w) begin
                z=1;
                Y=E;
            end
            else begin
                z=0;
                Y=A;
            end
            E:if(w) begin
                z=0;
                Y=C;
            end
            else begin
                z=0;
                Y=A;
            end
            default: begin
                z=0;
                Y=3'bxxx;
            end
        endcase

    //Defines the sequential block
    always @(negedge Resetn, posedge Clock) begin
         if(Resetn==0) y<=A;             //If a reset input occured, it goes back to the initial state A.
        else y<=Y;
    end

endmodule

Exercise2/Mealy/Clock_gen.v
`timescale 100us / 100us

module Clock_gen(clk);

parameter PERIOD = 10;

output reg clk;
	 
always
	begin: CLOCK_DRIVER
		clk <= 1'b0;
		#(PERIOD/2);
		clk <= 1'b1;
		#(PERIOD/2);
	end

endmodule

Exercise2/Mealy/Mealy00Tester.v

`timescale 100us / 100us

module Mealy00Tester ();

wire clk,out; 
reg resetn, in;            
reg [64:1] sequence;
integer i;
Clock_gen myClock(clk);
Mealy00 myMealy (clk,resetn,in,out);

initial in=0;
initial i=0;
initial resetn=1;


initial begin
sequence = 64'b1010001101010111010111101110100110110110111110101001111110111010;
  #640;
  $finish;
end

always @(posedge(clk)) begin

if(i<64) in <= sequence[64-i];
i=i+1;
$display("i=%d, Inputs: clk=%d, resetn=%d, in=%d. Outputs: out=%d",i,clk,resetn,in,out);
end

//To use gtkwave:
  reg dummy;
  reg[8*64:0] dumpfile_path = "mealy.vcd";

  initial begin
    dummy = $value$plusargs("VCD_PATH=%s", dumpfile_path);
    $dumpfile(dumpfile_path);
    $dumpvars(0,Mealy00Tester);
  end
  
endmodule

Exercise2/Mealy/output.vcd
$date
	Wed Nov 14 19:03:23 2018
$end
$version
	Icarus Verilog
$end
$timescale
	100us
$end
$scope module Mealy00Tester $end
$var wire 1 ! out $end
$var wire 1 " clk $end
$var reg 1 # dummy $end
$var reg 513 $ dumpfile_path [512:0] $end
$var reg 1 % in $end
$var reg 1 & resetn $end
$var reg 64 ' sequence [64:1] $end
$var integer 32 ( i [31:0] $end
$scope module myClock $end
$var reg 1 " clk $end
$scope begin CLOCK_DRIVER $end
$upscope $end
$upscope $end
$scope module myMealy $end
$var wire 1 " Clock $end
$var wire 1 & Resetn $end
$var wire 1 % w $end
$var reg 3 ) Y [3:1] $end
$var reg 3 * y [3:1] $end
$var reg 1 ! z $end
$upscope $end
$upscope $end
$enddefinitions $end
#0
$dumpvars
b0 *
b0 )
b0 (
b1010001101010111010111101110100110110110111110101001111110111010 '
1&
0%
b1101111011101010111010001110000011101010111010000101110011101100110001101100100 $
0#
0"
0!
$end
#5
b1 )
1%
b1 (
1"
#10
0"
#15
b0 )
b1 *
0%
b10 (
1"
#20
0"
#25
b1 )
b0 *
1%
b11 (
1"
#30
0"
#35
b0 )
b1 *
0%
b100 (
1"
#40
0"
#45
b0 *
b101 (
1"
#50
0"
#55
b110 (
1"
#60
0"
#65
b1 )
1%
b111 (
1"
#70
0"
#75
b10 )
b1 *
b1000 (
1"
#80
0"
#85
b11 )
b10 *
0%
b1001 (
1"
#90
0"
#95
b100 )
1!
b11 *
1%
b1010 (
1"
#100
0"
#105
b0 )
0!
b100 *
0%
b1011 (
1"
#110
0"
#115
b1 )
b0 *
1%
b1100 (
1"
#120
0"
#125
b0 )
b1 *
0%
b1101 (
1"
#130
0"
#135
b1 )
b0 *
1%
b1110 (
1"
#140
0"
#145
b10 )
b1 *
b1111 (
1"
#150
0"
#155
b10 *
b10000 (
1"
#160
0"
#165
b11 )
0%
b10001 (
1"
#170
0"
#175
b100 )
1!
b11 *
1%
b10010 (
1"
#180
0"
#185
b0 )
0!
b100 *
0%
b10011 (
1"
#190
0"
#195
b1 )
b0 *
1%
b10100 (
1"
#200
0"
#205
b10 )
b1 *
b10101 (
1"
#210
0"
#215
b10 *
b10110 (
1"
#220
0"
#225
b10111 (
1"
#230
0"
#235
b11 )
0%
b11000 (
1"
#240
0"
#245
b100 )
1!
b11 *
1%
b11001 (
1"
#250
0"
#255
b10 )
0!
b100 *
b11010 (
1"
#260
0"
#265
b10 *
b11011 (
1"
#270
0"
#275
b11 )
0%
b11100 (
1"
#280
0"
#285
b100 )
1!
b11 *
1%
b11101 (
1"
#290
0"
#295
b0 )
0!
b100 *
0%
b11110 (
1"
#300
0"
#305
b0 *
b11111 (
1"
#310
0"
#315
b1 )
1%
b100000 (
1"
#320
0"
#325
b10 )
b1 *
b100001 (
1"
#330
0"
#335
b11 )
b10 *
0%
b100010 (
1"
#340
0"
#345
b100 )
1!
b11 *
1%
b100011 (
1"
#350
0"
#355
b10 )
0!
b100 *
b100100 (
1"
#360
0"
#365
b11 )
b10 *
0%
b100101 (
1"
#370
0"
#375
b100 )
1!
b11 *
1%
b100110 (
1"
#380
0"
#385
b10 )
0!
b100 *
b100111 (
1"
#390
0"
#395
b11 )
b10 *
0%
b101000 (
1"
#400
0"
#405
b100 )
1!
b11 *
1%
b101001 (
1"
#410
0"
#415
b10 )
0!
b100 *
b101010 (
1"
#420
0"
#425
b10 *
b101011 (
1"
#430
0"
#435
b101100 (
1"
#440
0"
#445
b101101 (
1"
#450
0"
#455
b11 )
0%
b101110 (
1"
#460
0"
#465
b100 )
1!
b11 *
1%
b101111 (
1"
#470
0"
#475
b0 )
0!
b100 *
0%
b110000 (
1"
#480
0"
#485
b1 )
b0 *
1%
b110001 (
1"
#490
0"
#495
b0 )
b1 *
0%
b110010 (
1"
#500
0"
#505
b0 *
b110011 (
1"
#510
0"
#515
b1 )
1%
b110100 (
1"
#520
0"
#525
b10 )
b1 *
b110101 (
1"
#530
0"
#535
b10 *
b110110 (
1"
#540
0"
#545
b110111 (
1"
#550
0"
#555
b111000 (
1"
#560
0"
#565
b111001 (
1"
#570
0"
#575
b11 )
0%
b111010 (
1"
#580
0"
#585
b100 )
1!
b11 *
1%
b111011 (
1"
#590
0"
#595
b10 )
0!
b100 *
b111100 (
1"
#600
0"
#605
b10 *
b111101 (
1"
#610
0"
#615
b11 )
0%
b111110 (
1"
#620
0"
#625
b100 )
1!
b11 *
1%
b111111 (
1"
#630
0"
#635
b0 )
0!
b100 *
0%
b1000000 (
1"
