Exercise1/Mealy/tank_ctrl.v
module tank_ctrl (
    I,          //Sensor Inferior
    S,          //Sensor Superior
    B1,         //Bomba 1
    B2,         //Bomba 2
    clk,        //Clock
    reset       //Reset
    );

//Definición I/O
input I, S, clk, reset;
output B1, B2;

//Definición de Datos
    //Input Data Type
wire I, S, clk, reset;
    //Output DataType
reg B1, B2;

//Internal Variables
reg [1:0] curr_state;
wire [1:0] next_state;
reg use_pump;
wire T1,T2;

//Internal Constants
parameter FULL  =   2'b11;      //En este caso apago las 2 bombas
parameter HALF  =   2'b10;      //En este caso prendo la ultima en no activarse
parameter EMTPY =   2'b00;      //En este caso prendo ambas bombas
parameter ERROR =   2'b01;      //En este caso dejo las dos apagadas por seguridad

//Code
assign next_state = fsm_tank(curr_state, I, S);

//Function Code
function [1:0] fsm_tank;
    input [1:0] curr_state;
    input I;
    input S;
    case (curr_state)
        FULL: if(I == 1'b0 && S == 1'b0) begin
                fsm_tank = EMTPY;
                end
                else if (I == 1'b1 && S == 1'b0) begin
                fsm_tank = HALF;
                end
                else if (I == 1'b1 && S == 1'b1) begin
                fsm_tank = FULL;
                end
                else if (I == 1'b0 && S == 1'b1) begin
                fsm_tank = ERROR;
                end
        HALF: if(I == 1'b0 && S == 1'b0) begin
                fsm_tank = EMTPY;
                end
                else if (I == 1'b1 && S == 1'b0) begin
                fsm_tank = HALF;
                end
                else if (I == 1'b1 && S == 1'b1) begin
                fsm_tank = FULL;
                end
                else if (I == 1'b0 && S == 1'b1) begin
                fsm_tank = ERROR;
                end
        EMTPY: if(I == 1'b0 && S == 1'b0) begin
                fsm_tank = EMTPY;
                end
                else if (I == 1'b1 && S == 1'b0) begin
                fsm_tank = HALF;
                end
                else if (I == 1'b1 && S == 1'b1) begin
                fsm_tank = FULL;
                end
                else if (I == 1'b0 && S == 1'b1) begin
                fsm_tank = ERROR;
                end
        ERROR: if(I == 1'b0 && S == 1'b0) begin
                fsm_tank = EMTPY;
                end
                else if (I == 1'b1 && S == 1'b0) begin
                fsm_tank = HALF;
                end
                else if (I == 1'b1 && S == 1'b1) begin
                fsm_tank = FULL;
                end
                else if (I == 1'b0 && S == 1'b1) begin
                fsm_tank = ERROR;
                end
      default: fsm_tank = FULL;
    endcase
endfunction

//Sequential Logic
always @(posedge clk or reset)
begin: FSM_SEQ
    if(reset == 1'b1) begin
        curr_state <= #1 FULL;
    end 
    else begin
        curr_state <= #1 next_state;
    end
end


//Output Logic
always @(*)
begin: OUTPUT_LOGIC
    if (reset == 1'b1) begin
        B1 <= #1 1'b0;
        B2 <= #1 1'b0;
        use_pump <= #1 1'b1;
    end 
    else begin
        if(I == 1'b0 && S == 1'b0) begin    //empty
            B1 <= #1 1'b1;
            B2 <= #1 1'b1;
        end
        else if (I == 1'b0 && S == 1'b1) begin  //error
            B1 <= #1 1'b0;
            B2 <= #1 1'b0;
        end
        else if (I == 1'b1 && S == 1'b1) begin  //full
            B1 <= #1 1'b0;
            B2 <= #1 1'b0;
        end
        else if (I == 1'b1 && S == 1'b0) begin  //half
            B1 <= #1 !use_pump;
            B2 <= #1 use_pump;
        end
    end
end

xor(T1,curr_state[0],curr_state[1]);
and(T2,curr_state[1],T1);
always @(negedge T2 or reset)
begin
    if (reset == 1'b1) begin
        use_pump <= #1 1'b1;
    end
    use_pump <= #1 !use_pump;
end

endmodule

Exercise1/Mealy/tank_ctrl_tb.v
`include "./tank_ctrl.v"

module tank_ctrl_tb ();

//Inputs
reg I, S, clk, reset;

//Outputs
wire B1,B2;

tank_ctrl test_module (
    .I(I),          //Sensor Inferior
    .S(S),          //Sensor Superior
    .B1(B1),        //Bomba 1
    .B2(B2),        //Bomba 2
    .clk(clk),      //Clock
    .reset(reset)   //Reset
);

initial begin
    clk = 0;
    I = 0;
    S = 0;
    reset = 1;
    #5 reset = 0;
end

always begin
    #5 clk = !clk;
end

initial begin
  $dumpfile("tank.vcd");
  $dumpvars;
end

initial begin
  $display("Clk \tI \tS \tB1 \tB2");
  $monitor("%b\t%b\t%b\t%b\t%b",clk,I,S,B1,B2);
end

initial begin
    I=0; S=0;
    #10 I=1; S=0;
    #10 I=0; S=0;
    #10 I=1; S=0;
    #10 I=0; S=0;
    #10 I=1; S=0;
    #10 I=1; S=1;
    #10 I=1; S=0;
    #10 I=1; S=1;
    #10 I=1; S=0;
    #10 I=0; S=0;
    #10 I=1; S=0;
    #50 I=1; S=1;
    #10 I=0; S=1;
end

initial begin
  #200 $finish;
end

endmodule

Exercise1/Mealy/tank.vcd
$date
	Wed Nov  7 18:47:58 2018
$end
$version
	Icarus Verilog
$end
$timescale
	1s
$end
$scope module tank_ctrl_tb $end
$var wire 1 ! B1 $end
$var wire 1 " B2 $end
$var reg 1 # I $end
$var reg 1 $ S $end
$var reg 1 % clk $end
$var reg 1 & reset $end
$scope module test_module $end
$var wire 1 ' I $end
$var wire 1 ( S $end
$var wire 1 ) T1 $end
$var wire 1 * T2 $end
$var wire 1 + clk $end
$var wire 2 , next_state [1:0] $end
$var wire 1 - reset $end
$var reg 1 . B1 $end
$var reg 1 / B2 $end
$var reg 2 0 curr_state [1:0] $end
$var reg 1 1 use_pump $end
$scope function fsm_tank $end
$var reg 1 2 I $end
$var reg 1 3 S $end
$var reg 2 4 curr_state [1:0] $end
$var reg 2 5 fsm_tank [1:0] $end
$upscope $end
$scope begin FSM_SEQ $end
$upscope $end
$scope begin OUTPUT_LOGIC $end
$upscope $end
$upscope $end
$upscope $end
$enddefinitions $end
#0
$dumpvars
b11 5
bx 4
03
02
x1
bx 0
x/
x.
1-
b11 ,
0+
x*
x)
0(
0'
1&
0%
0$
0#
x"
x!
$end
#1
0*
0)
b0 ,
b0 5
b11 4
b11 0
x1
0/
0"
0.
0!
#2
x1
#3
11
#5
1%
1+
0&
0-
#6
b0 4
01
1/
1"
1.
1!
b0 0
#10
b10 ,
b10 5
12
0%
0+
1#
1'
#11
0/
0"
#15
1%
1+
#16
1*
1)
b10 4
b10 0
#20
b0 ,
b0 5
02
0%
0+
0#
0'
#21
1/
1"
#25
1%
1+
#26
0)
0*
b0 4
b0 0
#27
11
#30
b10 ,
b10 5
12
0%
0+
1#
1'
#31
0.
0!
#35
1%
1+
#36
1*
1)
b10 4
b10 0
#40
b0 ,
b0 5
02
0%
0+
0#
0'
#41
1.
1!
#45
1%
1+
#46
0)
0*
b0 4
b0 0
#47
01
#50
b10 ,
b10 5
12
0%
0+
1#
1'
#51
0/
0"
#55
1%
1+
#56
1*
1)
b10 4
b10 0
#60
b11 ,
b11 5
13
0%
0+
1$
1(
#61
0.
0!
#65
1%
1+
#66
0*
0)
b11 4
b11 0
#67
11
#70
b10 ,
b10 5
03
0%
0+
0$
0(
#71
1/
1"
#75
1%
1+
#76
1*
1)
b10 4
b10 0
#80
b11 ,
b11 5
13
0%
0+
1$
1(
#81
0/
0"
#85
1%
1+
#86
0*
0)
b11 4
b11 0
#87
01
#90
b10 ,
b10 5
03
0%
0+
0$
0(
#91
1.
1!
#95
1%
1+
#96
1*
1)
b10 4
b10 0
#100
b0 ,
b0 5
02
0%
0+
0#
0'
#101
1/
1"
#105
1%
1+
#106
0)
0*
b0 4
b0 0
#107
11
#110
b10 ,
b10 5
12
0%
0+
1#
1'
#111
0.
0!
#115
1%
1+
#116
1*
1)
b10 4
b10 0
#120
b11 ,
b11 5
13
0%
0+
1$
1(
#121
0/
0"
#125
1%
1+
#126
0*
0)
b11 4
b11 0
#127
01
#130
b1 ,
b1 5
02
0%
0+
0#
0'
#135
1%
1+
#136
1)
b1 4
b1 0
#140
0%
0+
#145
1%
1+
#150
b10 ,
b10 5
03
12
0%
0+
0$
0(
1#
1'
#151
1.
1!
#155
1%
1+
#156
1*
b10 4
b10 0
#160
b11 ,
b11 5
13
0%
0+
1$
1(
#161
0.
0!
#165
1%
1+
#166
0*
0)
b11 4
b11 0
#167
11
